Metadata-Version: 1.0
Name: stython
Version: 0.1.18
Summary: The Stython package
Home-page: https://github.com/cometcake575/stython
Author: Arun Kapila
Author-email: starshootercity@gmail.com
License: MIT License
